SmartEco/__init__.py
SmartEco/SmartML/__init__.py
SmartEco/SmartML/inspect.py
SmartEco/SmartML/model_evaluation.py
SmartEco/SmartML/model_splitting.py
SmartEco/SmartML/model_training.py
SmartEco/SmartML/smarteco_encoding.py
SmartEco/SmartML/models/BaseLine_Reg.py
SmartEco/SmartML/models/BaseLines_Class.py
SmartEco/SmartML/models/DL_Class.py
SmartEco/SmartML/models/DL_Reg.py
SmartEco/SmartML/models/SmartKNN.py
SmartEco/SmartML/models/Trees_Class.py
SmartEco/SmartML/models/Trees_Reg.py
SmartEco/SmartML/models/__init__.py
SmartEco/SmartML/models/base.py
SmartEco/SmartML/models/registry.py
SmartEco/tests/test_encoding.py
SmartEco/tests/test_evaluation.py
SmartEco/tests/test_imports.py
SmartEco/tests/test_registry.py
SmartEco/tests/test_smoke_classification.py
SmartEco/tests/test_smoke_regression.py
smarteco-0.1.1.dist-info/licenses/LICENSE
smarteco-0.1.1.dist-info/METADATA
smarteco-0.1.1.dist-info/WHEEL
smarteco-0.1.1.dist-info/top_level.txt
smarteco-0.1.1.dist-info/RECORD
