Metadata-Version: 2.4
Name: SmartEco
Version: 0.1.1
Summary: SmartEco ecosystem: CPU-first machine learning benchmarking and tooling
Author: SmartEco
License: MIT
Project-URL: Homepage, https://thatipamula-jashwanth.github.io/SmartEco/
Classifier: Programming Language :: Python :: 3
Classifier: License :: OSI Approved :: MIT License
Classifier: Operating System :: OS Independent
Requires-Python: >=3.9
License-File: LICENSE
Requires-Dist: numpy<3.0,>=1.23
Requires-Dist: pandas<3.0,>=1.5
Requires-Dist: scikit-learn<2.0,>=1.2
Requires-Dist: psutil<6.0,>=5.9
Requires-Dist: openml<1.0,>=0.14
Requires-Dist: smart-knn>=0.2.0
Provides-Extra: tree
Requires-Dist: lightgbm<5.0,>=4.0; extra == "tree"
Requires-Dist: xgboost<3.0,>=2.0; extra == "tree"
Requires-Dist: catboost<2.0,>=1.2; extra == "tree"
Provides-Extra: interpret
Requires-Dist: interpret<1.0,>=0.5; extra == "interpret"
Provides-Extra: dl
Requires-Dist: torch<3.0,>=2.0; extra == "dl"
Requires-Dist: pytorch-tabnet<5.0,>=4.1; extra == "dl"
Provides-Extra: all
Requires-Dist: lightgbm<5.0,>=4.0; extra == "all"
Requires-Dist: xgboost<3.0,>=2.0; extra == "all"
Requires-Dist: catboost<2.0,>=1.2; extra == "all"
Requires-Dist: interpret<1.0,>=0.5; extra == "all"
Requires-Dist: torch<3.0,>=2.0; extra == "all"
Requires-Dist: pytorch-tabnet<5.0,>=4.1; extra == "all"
Dynamic: license-file
